{
  "resourceType": "CodeSystem",
  "id": "fm-structure",
  "text": {
    "status": "generated",
    "div": "<div xmlns=\"http://www.w3.org/1999/xhtml\"><p>This code system http://fhir.cqgc.ferlab.bio/CodeSystem/fm-structure defines the following codes:</p><table class=\"codes\"><tr><td style=\"white-space:nowrap\"><b>Code</b></td><td><b>Display</b></td><td><b>Definition</b></td></tr><tr><td style=\"white-space:nowrap\">SOL<a name=\"fm-structure-SOL\"> </a></td><td>Solo</td><td>Family with only one member (proband alone)</td></tr><tr><td style=\"white-space:nowrap\">DUO<a name=\"fm-structure-DUO\"> </a></td><td>Duo</td><td>Family with two members</td></tr><tr><td style=\"white-space:nowrap\">TRI<a name=\"fm-structure-TRI\"> </a></td><td>Trio</td><td>Family with three members</td></tr><tr><td style=\"white-space:nowrap\">QUA<a name=\"fm-structure-QUA\"> </a></td><td>Quatuor</td><td>Family with four members</td></tr><tr><td style=\"white-space:nowrap\">QUI<a name=\"fm-structure-QUI\"> </a></td><td>Quintette</td><td>Family with five members</td></tr><tr><td style=\"white-space:nowrap\">SEX<a name=\"fm-structure-SEX\"> </a></td><td>Sextuor</td><td>Family with six members</td></tr><tr><td style=\"white-space:nowrap\">SEP<a name=\"fm-structure-SEP\"> </a></td><td>Septuor</td><td>Family with seven members</td></tr><tr><td style=\"white-space:nowrap\">OCT<a name=\"fm-structure-OCT\"> </a></td><td>Octuor</td><td>Family with eight members</td></tr><tr><td style=\"white-space:nowrap\">NON<a name=\"fm-structure-NON\"> </a></td><td>Nonette</td><td>Family with nine members</td></tr><tr><td style=\"white-space:nowrap\">DIX<a name=\"fm-structure-DIX\"> </a></td><td>Dixtuor</td><td>Family with ten members</td></tr></table></div>"
  },
  "url": "http://fhir.cqgc.ferlab.bio/CodeSystem/fm-structure",
  "version": "0.1.0",
  "name": "fm-structure",
  "title": "Family structure code system",
  "status": "draft",
  "experimental": false,
  "date": "2020-08-13T16:27:34-04:00",
  "publisher": "Ferlab.bio",
  "contact": [
    {
      "name": "Cqgc",
      "telecom": [
        {
          "system": "email",
          "value": "mailto:support@ferlab.bio"
        }
      ]
    }
  ],
  "description": "This field gives possible valueSet of the family structure",
  "caseSensitive": true,
  "content": "complete",
  "count": 10,
  "concept": [
    {
      "code": "SOL",
      "display": "Solo",
      "definition": "Family with only one member (proband alone)"
    },
    {
      "code": "DUO",
      "display": "Duo",
      "definition": "Family with two members"
    },
    {
      "code": "TRI",
      "display": "Trio",
      "definition": "Family with three members"
    },
    {
      "code": "QUA",
      "display": "Quatuor",
      "definition": "Family with four members"
    },
    {
      "code": "QUI",
      "display": "Quintette",
      "definition": "Family with five members"
    },
    {
      "code": "SEX",
      "display": "Sextuor",
      "definition": "Family with six members"
    },
    {
      "code": "SEP",
      "display": "Septuor",
      "definition": "Family with seven members"
    },
    {
      "code": "OCT",
      "display": "Octuor",
      "definition": "Family with eight members"
    },
    {
      "code": "NON",
      "display": "Nonette",
      "definition": "Family with nine members"
    },
    {
      "code": "DIX",
      "display": "Dixtuor",
      "definition": "Family with ten members"
    }
  ]
}