<?xml version="1.0" encoding="UTF-8"?>

<ValueSet xmlns="http://hl7.org/fhir">
  <id value="cgh-abnormalities"/>
  <text>
    <status value="generated"/><div xmlns="http://www.w3.org/1999/xhtml"><ul><li>Include all codes defined in <a href="CodeSystem-cgh-abnormalities.html"><code>http://fhir.cqgc.ferlab.bio/CodeSystem/cgh-abnormalities</code></a></li></ul></div>
  </text>
  <url value="http://fhir.cqgc.ferlab.bio/ValueSet/cgh-abnormalities"/>
  <version value="0.1.0"/>
  <name value="cgh-abnormalities"/>
  <title value="CGH abnormalities"/>
  <status value="draft"/>
  <experimental value="false"/>
  <date value="2022-07-20T15:49:15+00:00"/>
  <publisher value="Ferlab.bio"/>
  <contact>
    <name value="Cqgc"/>
    <telecom>
      <system value="email"/>
      <value value="mailto:support@ferlab.bio"/>
    </telecom>
  </contact>
  <description value="CGH abnormalities"/>
  <compose>
    <include>
      <system value="http://fhir.cqgc.ferlab.bio/CodeSystem/cgh-abnormalities"/>
    </include>
  </compose>
</ValueSet>